[
  {
    "id": 1,
    "hash": "079c67b",
    "text": "CMD Palette",
    "link": "/tools/",
    "date": "2026-01-31",
    "category": "feature"
  },
  {
    "id": 2,
    "hash": "079c67b",
    "text": "Mastermind game",
    "link": "/tools/",
    "date": "2026-01-31",
    "category": "feature"
  },
  {
    "id": 3,
    "hash": "079c67b",
    "text": "Stripe tips",
    "link": "/tools/",
    "date": "2026-01-31",
    "category": "integration"
  },
  {
    "id": 4,
    "hash": "99ed221",
    "text": "Skip links + ARIA",
    "link": "/",
    "date": "2026-01-31",
    "category": "a11y"
  },
  {
    "id": 5,
    "hash": "99ed221",
    "text": "Image compression",
    "link": "/",
    "date": "2026-01-31",
    "category": "feature"
  },
  {
    "id": 6,
    "hash": "99ed221",
    "text": "Mobile full-bleed",
    "link": "/",
    "date": "2026-01-31",
    "category": "design"
  },
  {
    "id": 7,
    "hash": "ebaf3f3",
    "text": "Custom domain",
    "link": "/",
    "date": "2026-02-01",
    "category": "integration"
  },
  {
    "id": 8,
    "hash": "536a0b4",
    "text": "The Single Cabinet",
    "link": "/",
    "date": "2026-02-01",
    "category": "design"
  },
  {
    "id": 9,
    "hash": "536a0b4",
    "text": "Scanlines + grain",
    "link": "/",
    "date": "2026-02-01",
    "category": "design"
  },
  {
    "id": 10,
    "hash": "536a0b4",
    "text": "Typing effect",
    "link": "/",
    "date": "2026-02-01",
    "category": "feature"
  },
  {
    "id": 11,
    "hash": "536a0b4",
    "text": "Ghost cabinets",
    "link": "/",
    "date": "2026-02-01",
    "category": "design"
  },
  {
    "id": 12,
    "hash": "536a0b4",
    "text": "Screen glow",
    "link": "/",
    "date": "2026-02-01",
    "category": "design"
  },
  {
    "id": 13,
    "hash": "8e11961",
    "text": "Forkiverse link",
    "link": "/",
    "date": "2026-02-01",
    "category": "fix"
  },
  {
    "id": 14,
    "hash": "a81a070",
    "text": "Constellation changelog",
    "link": "/changelog/",
    "date": "2026-02-02",
    "category": "feature"
  },
  {
    "id": 15,
    "hash": "a81a070",
    "text": "Agent coordination",
    "link": "/changelog/",
    "date": "2026-02-02",
    "category": "feature"
  }
]
